[
  {
    "employer_name": "Micron Technology",
    "job_title": "Supply Chain Engineer",
    "job_city": "Boise",
    "job_state": "ID",
    "job_posted_at": "19h",
    "job_description": "• Less than 2 years FE Capital Supplier ManagerTaichung City, Taichung City, Taiwan + 2 morePosted 6 months ago Senior Construction Supply Chain Project ManagerSanand, Gujarat, IndiaPosted a month ago Category Supplier ManagerBoise, Idaho, United States of AmericaPosted a month ago Supply Chain ManagerPerai, Pulau Pinang (Penang), MalaysiaPosted a month ago Global Facilities Cost Program ManagerSingapore, SingaporePosted a month ago Senior Planning EngineerSanand, Gujarat, IndiaPosted 2 months ago ATSM SUPPLY MANAGER, SMTSanand, Gujarat, IndiaPosted a month ago.",
    "job_apply_link": "https://careers.micron.com/careers/job/38635451",
    "id": "micron-technology-supply-chain-engineer-boise"
  }
]