[
  {
    "employer_name": "Synopsys",
    "job_title": "Software Engineer - User Interface (Exton, PA)",
    "job_city": "Exton",
    "job_state": "PA",
    "job_posted_at": "1d",
    "job_description": "• Engaging with strategic customers and partners to understand their needs, translating market requirements into actionable solutions and roadmaps.\n• Elevate the user experience of AGI’s flagship Systems Tool Kit, enabling customers to tackle complex modeling and simulation challenges.\n• Bridge customer needs and product capabilities, delivering solutions that meet real-world requirements and exceed expectations.\n• If you do not allow these cookies, you will experience less targeted advertising.\n• Extensive experience in user interface development for complex software products.\n• Strong analytical and problem-solving skills, with experience in coordinating across multiple products or teams.\n• Sitemap Modify Preferences Test & Validation Engineer, Staff Austin, Texas Principal Verification Design Engineer United States Sr.\n• Leading the planning, architecture, and research efforts across multiple software projects or disciplines, setting technical direction and vision.",
    "job_apply_link": "https://careers.synopsys.com/job/exton/software-engineer-user-interface-exton-pa/44408/87085294864",
    "id": "synopsys-software-engineer-user-interface-exton-pa-exton"
  }
]