[
  {
    "job_title": "Software Engineering, Realtime Engines",
    "employer_name": "Meta",
    "job_city": "Bellevue",
    "job_state": "WA +2 locations",
    "job_description": "Engineering",
    "job_apply_link": "https://www.metacareers.com/jobs/1480762142943343",
    "job_posted_at": "Recently",
    "job_posted_at_datetime_utc": "Recently",
    "id": "meta-software-engineering-realtime-engines-bellevue"
  },
  {
    "job_title": "Staff Engineer, RFA Forward Deployed Engineering",
    "employer_name": "Stripe",
    "job_city": "Seattle",
    "job_state": "CA",
    "job_description": "Join Stripe to help build the economic infrastructure for the internet.",
    "job_apply_link": "https://stripe.com/jobs/search?gh_jid=7154047",
    "job_posted_at_datetime_utc": "2025-08-18T18:43:12.000Z",
    "job_employment_type": "FULLTIME",
    "id": "stripe-staff-engineer-rfa-forward-deployed-engineering-seattle"
  },
  {
    "job_title": "Senior Software Engineer, Growth Platform",
    "employer_name": "Airbnb",
    "job_city": "United States",
    "job_state": "CA",
    "job_description": "Join Airbnb to create a world where anyone can belong anywhere.",
    "job_apply_link": "https://careers.airbnb.com/positions/7175614?gh_jid=7175614",
    "job_posted_at_datetime_utc": "2025-08-18T18:07:56.000Z",
    "job_employment_type": "FULLTIME",
    "id": "airbnb-senior-software-engineer-growth-platform-united-states"
  }
]