[
  {
    "employer_name": "Siemens",
    "job_title": "Logistics Engineering Co-op - Spring 2026 (UT Arlington)",
    "job_city": "Grand Prairie",
    "job_state": "Texas",
    "job_posted_at": "1d",
    "job_description": "software engineering job for the role Logistics Engineering Co-op - Spring 2026 (UT Arlington)",
    "job_apply_link": "https://jobs.siemens.com/careers",
    "id": "siemens-logistics-engineering-co-op-spring-2026-ut-arlington-grand-prairie"
  },
  {
    "employer_name": "Guidehouse",
    "job_title": "DoD Business Analytics Engineer",
    "job_city": "US - FL",
    "job_state": "Tampa",
    "job_posted_at": "1d",
    "job_description": "• Software EngineerlocationsUS - VA, Springfieldposted onPosted 30+ Days Ago30414Software Engineerlocations2 Locationsposted onPosted 15 Days Ago31684SailPoint EngineerlocationsUS - Remote (Any location)posted onPosted 2 Days Ago31299Software QA Journeyman – Integration Testing Engineerlocations8 Locationsposted onPosted Yesterday31656AWS Data EngineerlocationsUS - Remote (Any location)posted onPosted 28 Days Ago31815Senior Automation Engineerlocations2 Locationsposted onPosted 3 Days Ago32300Sr.\n• Application DeveloperlocationsUS - Remote (Any location)posted onPosted Yesterday32574Senior Technical Lead – Data EngineeringlocationsGH Office: Tysons Corner, VA (Headquarters)posted onPosted 11 Days Ago32053Software Quality Assurance Testerslocations8 Locationsposted onPosted Yesterday31389Journeyman Software Quality Assurance Testerlocations8 Locationsposted onPosted Yesterday31383Senior Full Stack DeveloperlocationsUS - Remote (Any location)posted onPosted 30+ Days Ago30471Senior Full Stack Developerlocations2 Locationsposted onPosted 22 Days Ago31629Senior Full Stack Developerlocations2 Locationsposted onPosted 30+ Days Ago31261Data Engineer ArchitectlocationsUS - AL, Huntsvilleposted onPosted Yesterday31270Senior Cloud Infrastructure EngineerlocationsIN - Trivandrumposted onPosted 30+ Days Ago29665Senior Data Engineerlocations2 Locationsposted onPosted 3 Days Ago29225Cyber Security EngineerlocationsUS - Remote (Any location)posted onPosted Yesterday32174Senior Aerospace Systems EngineerlocationsUS - OH, Beavercreekposted onPosted 2 Days Ago29948Quality Assurance Engineer-Automationlocations2 Locationsposted onPosted Today30925DoD Business Analytics EngineerlocationsUS - FL, Tampaposted onPosted Yesterday32570.",
    "job_apply_link": "https://guidehouse.wd1.myworkdayjobs.com/en-US/External/job/US---FL-Tampa/DoD-Business-Analytics-Engineer_32570?q=software+engineering&Location_Country=bc33aa3152ec42d4995f4791a106ed09",
    "id": "guidehouse-dod-business-analytics-engineer-us-fl"
  },
  {
    "employer_name": "ABB",
    "job_title": "Front End Developer",
    "job_city": "Available in one of 2 locations",
    "job_state": "US",
    "job_posted_at": "1h",
    "job_description": "• Products Products Control Room Solutions Drives Electric Vehicle Charging Infrastructure Low Voltage Products and Systems Measurement and Analytics Mechanical Power Transmission Medium Voltage Products Metallurgy Products Motors and Generators PLC Automation Power Converters and Inverters Robotics See all products and systems Systems Control Systems Operations Management Software Power Electronics Safety Turbocharging UPS and Power Conditioning See all products and systems Industries Industries Aluminium Automotive Buildings and Infrastructure Cement Channel Partners Chemical Data Centers Food and Beverage Process Automation Life Sciences Marine and Ports Metals Mining Oil and Gas Ports Power Generation Printing Pulp and Paper Railway Smart Cities Solar Power Water Wind Power See all industries and utilities Services Your Needs Rapid response Lifecycle management Performance improvement Operational excellence Service for products and systems Service Offering Advanced Services End of Life Services Engineering and Consulting Extensions, Upgrades and Retrofits Installation and Commissioning Maintenance Replacement Service Agreements Spares and Consumables Technical support and repairs Training Service for products and systems Service for Products and Systems Control Systems Drives Electric Vehicle Charging Infrastructure Low Voltage Products and Systems Measurement and Analytics Medium Voltage Products and Systems Motors and Generators Power Converters and Inverters Power Electronics Robotics Turbocharging UPS and Power Conditioning Service for products and systems About Us Who we are About ABB Our strategy Our purpose Our values Our engagements and partnerships Integrity Diversity & Inclusion Corporate governance Board of Directors Executive Committee Quarterly results and annual reports COVID-19 information About ABB Our businesses Electrification Process Automation Motion Robotics & Discrete Automation Technology & Innovation ABB Ability™ Cyber security Innovations ABB International Nobel Partnership ABB Research Award ABB Technology Ventures ABB Review Corporate research University collaboration Sustainability Our approach Sustainability strategy 2030 Enabling a low-carbon society Preserving resources Promoting social progress Where to buy ABB Ability Marketplace™ Channel Partners Search for an ABB partner Supplying to ABB Social Media ABB Conversations Facebook Instagram LinkedIn Twitter YouTube ABB Formula E ABB FIA Formula E World Championship The partnership The pioneers Drivers of progress News & Media Careers Investors Contact Us Who we are About ABB Our strategy Our purpose Our values Our engagements and partnerships Integrity Diversity & Inclusion Corporate governance Board of Directors Executive Committee Quarterly results and annual reports COVID-19 information About ABB Our businesses Electrification Process Automation Motion Robotics & Discrete Automation Technology & Innovation ABB Ability™ Cyber security Innovations ABB International Nobel Partnership ABB Research Award ABB Technology Ventures ABB Review Corporate research University collaboration Sustainability Our approach Sustainability strategy 2030 Enabling a low-carbon society Preserving resources Promoting social progress Where to buy ABB Ability Marketplace™ Channel Partners Search for an ABB partner Supplying to ABB Social Media ABB Conversations Facebook Instagram LinkedIn Twitter YouTube ABB Formula E ABB FIA Formula E World Championship The partnership The pioneers Drivers of progress Your Needs Rapid response Lifecycle management Performance improvement Operational excellence Service for products and systems Service Offering Advanced Services End of Life Services Engineering and Consulting Extensions, Upgrades and Retrofits Installation and Commissioning Maintenance Replacement Service Agreements Spares and Consumables Technical support and repairs Training Service for products and systems Service for Products and Systems Control Systems Drives Electric Vehicle Charging Infrastructure Low Voltage Products and Systems Measurement and Analytics Medium Voltage Products and Systems Motors and Generators Power Converters and Inverters Power Electronics Robotics Turbocharging UPS and Power Conditioning Service for products and systems Careers Explore ABB Life at ABB Diversity, Equity and Inclusion We grow How to apply Professionals Graduates & Entry level Students Job Search Events Blog Explore ABB Life at ABB Diversity, Equity and Inclusion We grow How to apply Professionals Graduates & Entry level Students Job Search Events Blog ABB Ability™ Cyber security Innovations ABB International Nobel Partnership ABB Research Award ABB Technology Ventures ABB Review Corporate research University collaboration Careers Explore ABB Life at ABB Diversity & Inclusion We grow How to apply Professionals Graduates & Entry level Students Job Search Events Blog Customer events News & media Who we are Innovation Careers Sustainability Our values Supplying EEO and Affirmative Action Our approach Sustainability strategy 2030 Enabling a low-carbon society Preserving resources Promoting social progress ABB Ability Marketplace™ Channel Partners Search for an ABB partner Supplying to ABB.",
    "job_apply_link": "https://careers.abb/global/en/job/JR00001806/Front-End-Developer",
    "id": "abb-front-end-developer-available-in-one-of-2-locations"
  },
  {
    "employer_name": "Honeywell",
    "job_title": "Mobile Application developer II - iOS, Azure",
    "job_city": "Phoenix",
    "job_state": "AZ",
    "job_posted_at": "19h",
    "job_description": "• The ideal candidate will have experience in Microchip firmware (MPLAB, Harmony), embedded Linux (ARM SoCs, Quartus), C++ GUI development with Qt, and networking (TCP/UDP).\n• You'll translate customer needs into technical solutions and support project development end-to-end.\n• Security clearance eligibility required (DoD preferred).\n• Collaborate with cross-functional teams to meet software engineering requirements.\n• Sr Advanced Software Engr Locations Richmond, VA, United States (Hybrid) Posting Date09/18/2025 Advanced Software Engr Locations Atlanta, GA, United States (Hybrid) Posting Date09/22/2025 Advanced Software Engr Locations Atlanta, GA, United States (Hybrid) Posting Date08/11/2025 Trending Software Engineer & Computer Science - Recent Grad/Full Time Locations United States Posting Date08/29/2025 Trending As a Recent Graduate here at Honeywell, you will have the opportunity to kickstart your career by working alongside experienced professionals in a dynamic and innovative environment.\n• Software Engineer & Computer Science - Summer 2026 Intern (US Person Required) Locations United States Posting Date08/29/2025 Trending Through hands-on learning experiences, global exposure, networking, and professional development opportunities, Honeywell interns will shape the future.\n• You’ll have the opportunity to work alongside industry experts, lead initiatives that refine technical skills, and have unparalleled mentorship and growth opportunities that will elevate your career.\n• Software Engineer & Computer Science - Recent Grad/Full Time (US Person Required) Locations United States Posting Date08/29/2025 Trending As a Recent Graduate here at Honeywell, you will have the opportunity to kickstart your career by working alongside experienced professionals in a dynamic and innovative environment.",
    "job_apply_link": "https://careers.honeywell.com/en/sites/Honeywell/job/118690/?keyword=software+engineering&location=United+States&locationId=300000000469866&locationLevel=country&mode=location",
    "id": "honeywell-mobile-application-developer-ii-ios-azure-phoenix"
  },
  {
    "employer_name": "Honeywell",
    "job_title": "Mobile app developer I - iOS, Azure",
    "job_city": "Phoenix",
    "job_state": "AZ",
    "job_posted_at": "19h",
    "job_description": "• The ideal candidate will have experience in Microchip firmware (MPLAB, Harmony), embedded Linux (ARM SoCs, Quartus), C++ GUI development with Qt, and networking (TCP/UDP).\n• You'll translate customer needs into technical solutions and support project development end-to-end.\n• Security clearance eligibility required (DoD preferred).\n• Collaborate with cross-functional teams to meet software engineering requirements.\n• Sr Advanced Software Engr Locations Richmond, VA, United States (Hybrid) Posting Date09/18/2025 Advanced Software Engr Locations Atlanta, GA, United States (Hybrid) Posting Date09/22/2025 Advanced Software Engr Locations Atlanta, GA, United States (Hybrid) Posting Date08/11/2025 Trending Software Engineer & Computer Science - Recent Grad/Full Time Locations United States Posting Date08/29/2025 Trending As a Recent Graduate here at Honeywell, you will have the opportunity to kickstart your career by working alongside experienced professionals in a dynamic and innovative environment.\n• Software Engineer & Computer Science - Summer 2026 Intern (US Person Required) Locations United States Posting Date08/29/2025 Trending Through hands-on learning experiences, global exposure, networking, and professional development opportunities, Honeywell interns will shape the future.\n• You’ll have the opportunity to work alongside industry experts, lead initiatives that refine technical skills, and have unparalleled mentorship and growth opportunities that will elevate your career.\n• Software Engineer & Computer Science - Recent Grad/Full Time (US Person Required) Locations United States Posting Date08/29/2025 Trending As a Recent Graduate here at Honeywell, you will have the opportunity to kickstart your career by working alongside experienced professionals in a dynamic and innovative environment.",
    "job_apply_link": "https://careers.honeywell.com/en/sites/Honeywell/job/118688/?keyword=software+engineering&location=United+States&locationId=300000000469866&locationLevel=country&mode=location",
    "id": "honeywell-mobile-app-developer-i-ios-azure-phoenix"
  }
]